tests/__init__.py
tests/test_table_docstrings.py
hei_planning_system-0.2.1.dist-info/LICENSE
hei_planning_system-0.2.1.dist-info/METADATA
hei_planning_system-0.2.1.dist-info/WHEEL
hei_planning_system-0.2.1.dist-info/entry_points.txt
hei_planning_system-0.2.1.dist-info/top_level.txt
hei_planning_system-0.2.1.dist-info/RECORD
