Metadata-Version: 2.1
Name: hei-planning-system
Version: 0.2.1
Summary: HE Planning Suite.
Home-page: https://github.com/jehboyes/planning_system
Author: James Boyes
Author-email: James.Boyes@lcm.ac.uk
License: UNKNOWN
Platform: UNKNOWN
License-File: LICENSE
